zygoat/__init__.py
zygoat/cli.py
zygoat/components/__init__.py
zygoat/components/backend/__init__.py
zygoat/components/backend/banditrc.py
zygoat/components/backend/black.py
zygoat/components/backend/cache.py
zygoat/components/backend/dependencies.py
zygoat/components/backend/docker_compose.py
zygoat/components/backend/dockerfile.py
zygoat/components/backend/flake8/__init__.py
zygoat/components/backend/flake8/configuration.py
zygoat/components/backend/flake8/resources/.flake8
zygoat/components/backend/flake8/resources/__init__.py
zygoat/components/backend/gitignore.py
zygoat/components/backend/pytest.py
zygoat/components/backend/reformat.py
zygoat/components/backend/resources/.banditrc
zygoat/components/backend/resources/Dockerfile
zygoat/components/backend/resources/Dockerfile.local
zygoat/components/backend/resources/__init__.py
zygoat/components/backend/resources/docker-compose.cache.yml
zygoat/components/backend/resources/docker-compose.yml
zygoat/components/backend/resources/gunicorn.conf.py
zygoat/components/backend/resources/pytest.ini
zygoat/components/backend/settings/__init__.py
zygoat/components/backend/settings/installed_apps.py
zygoat/components/base.py
zygoat/components/docker_compose.py
zygoat/components/editorconfig.py
zygoat/components/file_component.py
zygoat/components/frontend/__init__.py
zygoat/components/frontend/cypress/__init__.py
zygoat/components/frontend/cypress/configuration.py
zygoat/components/frontend/cypress/gitignore.py
zygoat/components/frontend/cypress/resources/.gitignore
zygoat/components/frontend/cypress/resources/__init__.py
zygoat/components/frontend/cypress/resources/cypress.json
zygoat/components/frontend/dependencies/__init__.py
zygoat/components/frontend/dependencies/jest_config.py
zygoat/components/frontend/dependencies/jest_setup.py
zygoat/components/frontend/dependencies/mui.py
zygoat/components/frontend/dependencies/resources/__init__.py
zygoat/components/frontend/dependencies/resources/_app.js
zygoat-1.20.0.dist-info/LICENSE
zygoat-1.20.0.dist-info/METADATA
zygoat-1.20.0.dist-info/WHEEL
zygoat-1.20.0.dist-info/entry_points.txt
zygoat-1.20.0.dist-info/RECORD
