Metadata-Version: 2.1
Name: zygoat
Version: 1.20.0
Summary: 
Author: Bequest, Inc.
Author-email: oss@willing.com
Requires-Python: >=3.9,<4.0
Classifier: Programming Language :: Python :: 3
Classifier: Programming Language :: Python :: 3.9
Classifier: Programming Language :: Python :: 3.10
Classifier: Programming Language :: Python :: 3.11
Requires-Dist: click (>=8.1.7,<9.0.0)
Requires-Dist: colorama (>=0.4.4,<0.5.0)
Requires-Dist: importlib-metadata (>=6.8.0,<7.0.0)
Requires-Dist: python-box[all] (>=7.1.1,<8.0.0)
Requires-Dist: redbaron (>=0.9.2,<0.10.0)
Requires-Dist: requests (>=2.31.0,<3.0.0)
Requires-Dist: rtd-poetry (>=0.1.0,<0.2.0)
Requires-Dist: ruamel.yaml (>=0.17.10,<0.18.0)
Requires-Dist: semver (>=3.0.2,<4.0.0)
Requires-Dist: toml (>=0.10.2,<0.11.0)
Requires-Dist: virtualenv (>=20.24.6,<21.0.0)
Project-URL: Documentation, https://zygoat.readthedocs.io/en/latest/
